context_engineering_mcp/__init__.py
context_engineering_mcp/server.py
context_engineering_mcp/templates.py
context_engineering_mcp/cognitive/__init__.py
context_engineering_mcp/cognitive/thinking_models.py
context_engineering_mcp/core/__init__.py
context_engineering_mcp/core/atoms.py
context_engineering_mcp/core/cells.py
context_engineering_mcp/core/molecules.py
context_engineering_mcp/core/programs.py
context_engineering_mcp/systems/__init__.py
context_engineering_mcp/systems/organs.py
context_engineering_mcp-0.1.1.dist-info/METADATA
context_engineering_mcp-0.1.1.dist-info/WHEEL
context_engineering_mcp-0.1.1.dist-info/entry_points.txt
context_engineering_mcp-0.1.1.dist-info/licenses/LICENSE
context_engineering_mcp-0.1.1.dist-info/RECORD
