Metadata-Version: 2.4
Name: context-engineering-mcp
Version: 0.1.1
Summary: MCP server for Context Engineering templates and protocols
License-File: LICENSE
Requires-Python: >=3.10
Requires-Dist: mcp>=1.0.0
Requires-Dist: pydantic>=2.0.0
Provides-Extra: dev
Requires-Dist: mypy>=1.0.0; extra == 'dev'
Requires-Dist: pytest>=7.0.0; extra == 'dev'
Requires-Dist: ruff>=0.1.0; extra == 'dev'
